{
	"email": "vhfmag@protonmail.com",
	"social": [
		{
			"serviceName": "linkedin",
			"icon": "fa-linkedin",
			"url": "https://www.linkedin.com/in/vhfmag"
		},
		{
			"serviceName": "twitter",
			"icon": "fa-twitter",
			"url": "https://twitter.com/vhfmag"
		},
		{
			"serviceName": "gitlab",
			"icon": "fa-gitlab",
			"url": "https://gitlab.com/vhfmag/"
		},
		{
			"serviceName": "pocket",
			"icon": "fa-get-pocket",
			"url": "https://getpocket.com/@vhfmag"
		},
		{
			"serviceName": "github",
			"icon": "fa-github",
			"url": "https://github.com/vhfmag/"
		},
		{
			"serviceName": "instagram",
			"icon": "fa-instagram",
			"url": "https://instagram.com/vhfmag"
		},
		{
			"serviceName": "keybase",
			"icon": "fa-key",
			"url": "https://keybase.io/vhfmag"
		}
	]
}
